manga_ocr/__init__.py
manga_ocr/__main__.py
manga_ocr/ocr.py
manga_ocr/run.py
manga_ocr_abang-0.2.0.dist-info/LICENSE
manga_ocr_abang-0.2.0.dist-info/METADATA
manga_ocr_abang-0.2.0.dist-info/WHEEL
manga_ocr_abang-0.2.0.dist-info/entry_points.txt
manga_ocr_abang-0.2.0.dist-info/top_level.txt
manga_ocr_abang-0.2.0.dist-info/RECORD
