Metadata-Version: 2.1
Name: manga-ocr-abang
Version: 0.2.0
Summary: OCR for Japanese manga
Home-page: https://github.com/AbangTanYiHan/manga-ocr-abang
Author: Abang
Author-email: shinichiconan1997@gmail.com
License: Apache License 2.0
Classifier: Programming Language :: Python :: 3
License-File: LICENSE
Requires-Dist: fire
Requires-Dist: fugashi
Requires-Dist: jaconv
Requires-Dist: loguru
Requires-Dist: numpy
Requires-Dist: Pillow
Requires-Dist: pyperclip
Requires-Dist: sentencepiece
Requires-Dist: torch (>=1.0)
Requires-Dist: transformers (>=4.12.5)
Requires-Dist: unidic-lite
